dataip/__init__.py
dataip-1.0.3.dist-info/LICENSE.txt
dataip-1.0.3.dist-info/METADATA
dataip-1.0.3.dist-info/WHEEL
dataip-1.0.3.dist-info/top_level.txt
dataip-1.0.3.dist-info/RECORD
