Metadata-Version: 2.1
Name: dataip
Version: 1.0.3
Summary: dataip package is used to gather information based on your IP address
Home-page: UNKNOWN
Author: Aditya Khemka
License: MIT
Keywords: ip,aditya,khemka,aditya khemka,ipinfo,ip address,python,ipdata,dataip
Platform: UNKNOWN
Classifier: License :: OSI Approved :: MIT License
Classifier: Programming Language :: Python :: 3
Requires-Dist: requests
